[null,{"name":"Play","permissions":"NONE","restriction":"0","_id":"ABpkY","actions":[{"channel":"0","varName":"","name":"Join Voice Channel"},{"token":"","user":"","pass":"","url":"https://www.googleapis.com/youtube/v3/search?part=snippet&q=${slashParams(\"song\")}&type=video&key=AIzaSyB9uIZpPTB9E4BWNk_WdLw8mWav3cQXrb0","path":"items[0].snippet.title","storage":"1","varName":"sr-y-1","debugMode":"0","headers":"","reUse":"1","name":"Store Json From WebAPI"},{"token":"","user":"","pass":"","url":"https://www.googleapis.com/youtube/v3/search?part=snippet&q=${slashParams(\"song\")}&type=video&key=AIzaSyB9uIZpPTB9E4BWNk_WdLw8mWav3cQXrb0","path":"items[0].id.videoId","storage":"1","varName":"sid-y-1","debugMode":"0","headers":"","reUse":"1","name":"Store Json From WebAPI"},{"token":"","user":"","pass":"","url":"https://www.googleapis.com/youtube/v3/search?part=snippet&q=${slashParams(\"song\")}&type=video&key=AIzaSyB9uIZpPTB9E4BWNk_WdLw8mWav3cQXrb0","path":"items[0].snippet.thumbnails.high.url","storage":"1","varName":"stn-y-1","debugMode":"0","headers":"","reUse":"1","name":"Store Json From WebAPI"},{"token":"","user":"","pass":"","url":"https://www.googleapis.com/youtube/v3/videos?id=${slashParams(\"song\")}&part=contentDetails&key=AIzaSyB9uIZpPTB9E4BWNk_WdLw8mWav3cQXrb0","path":"items[0].contentDetails.duration","storage":"1","varName":"sd-y-1","debugMode":"0","headers":"","reUse":"1","name":"Store Json From WebAPI"},{"url":"${tempVars(\"sid-y-1\")}","seek":"0","volume":"100","bitrate":"192","type":"0","name":"Play YouTube Video"},{"channel":"0","varName":"","message":"","buttons":[],"selectMenus":[],"attachments":[],"embeds":[{"title":"Успешно добавлено в очередь!","url":"","color":"#70ff00","timestamp":"true","imageUrl":"","thumbUrl":"https://media.discordapp.net/attachments/971187560170790952/978464860750901288/Rythm_Green.png","description":"Ваш трек был добавлен в очередь!\n\nТрек: **${tempVars(\"sr-y-1\")}**","fields":[],"author":"","authorUrl":"","authorIcon":"","footerText":"Rythm Green Music","footerIconUrl":"https://cdn.discordapp.com/attachments/971187560170790952/978442340635136040/711.gif"}],"reply":true,"ephemeral":true,"tts":false,"overwrite":false,"dontSend":false,"editMessage":"0","editMessageVarName":"","storage":"0","varName2":"","name":"Send Message"},{"storage":"2","varName":"queue","name":"Create List"},{"storage":"2","varName":"queue-id","name":"Create List"},{"storage":"2","varName":"queue-id","addType":"0","position":"","value":"tempVars(\"sid-y-1\")","name":"Add Item to List"},{"storage":"2","varName":"queue","addType":"0","position":"","value":"tempVars(\"sr-y-1\")","name":"Add Item to List"},{"server":"0","varName":"","dataName":"playing-count","comparison":"1","value":"1","iftrue":"0","iftrueVal":"","iffalse":"1","iffalseVal":"","name":"Check Server Data"}],"comType":"4","_aliases":[],"parameters":[{"name":"song","description":"Название или ссылка на трек ","type":"STRING","required":true,"choices":null}],"description":"Поиск музыки и воспроизведение в голосовом канале 🎵"},{"name":"Install","permissions":"NONE","permissions2":"NONE","restriction":"4","_id":"StUTr","actions":[{"channel":"0","varName":"","message":"","buttons":[{"name":"","type":"SECONDARY","id":"msg-button-30e665a","row":"","url":"","emoji":"⏹️","mode":"PERSISTENT","time":"","actions":[{"name":"Leave Voice Channel"},{"server":"0","varName":"","dataName":"${tempVars(\"skipped\")}-skipped","changeType":"0","value":"1","name":"Control Server Data"},{"storage":"2","varName":"queue","removeType":"1","position":"","storage2":"0","varName2":"","name":"Remove Item from List"},{"storage":"2","varName":"queue-id","removeType":"1","position":"","storage2":"0","varName2":"","name":"Remove Item from List"},{"amount":"600","name":"Skip Queue"}]},{"name":"","type":"SECONDARY","id":"msg-button-ebe1084","row":"","url":"","emoji":"⏩","mode":"PERSISTENT","time":"","actions":[{"server":"0","varName":"","dataName":"${tempVars(\"skipped\")}-skipped","changeType":"0","value":"1","name":"Control Server Data"},{"storage":"2","varName":"queue","removeType":"1","position":"","storage2":"0","varName2":"","name":"Remove Item from List"},{"storage":"2","varName":"queue-id","removeType":"1","position":"","storage2":"0","varName2":"","name":"Remove Item from List"},{"amount":"1","name":"Skip Queue"}]}],"selectMenus":[],"attachments":[],"embeds":[{"title":"Панель музыки","url":"","color":"#70ff00","timestamp":"false","imageUrl":"","thumbUrl":"https://cdn.discordapp.com/attachments/971187560170790952/978464860750901288/Rythm_Green.png","description":"Управление треками!","fields":[],"author":"","authorUrl":"","authorIcon":"","footerText":"","footerIconUrl":""}],"reply":true,"ephemeral":false,"tts":false,"overwrite":false,"dontSend":false,"editMessage":"0","editMessageVarName":"","storage":"0","varName2":"","name":"Send Message"}],"comType":"4","description":"Создание панели для управления треками "}]